PytestZhongwenWendang/README.md
PytestZhongwenWendang/__init__.py
PytestZhongwenWendang/__main__.py
PytestZhongwenWendang/file.epub
PytestZhongwenWendang/index.html
PytestZhongwenWendang/css/__init__.py
PytestZhongwenWendang/css/annotations.css
PytestZhongwenWendang/css/main.css
PytestZhongwenWendang/css/normalize.css
PytestZhongwenWendang/css/popup.css
PytestZhongwenWendang/font/__init__.py
PytestZhongwenWendang/font/fontello.eot
PytestZhongwenWendang/font/fontello.svg
PytestZhongwenWendang/font/fontello.ttf
PytestZhongwenWendang/font/fontello.woff
PytestZhongwenWendang/img/__init__.py
PytestZhongwenWendang/img/annotator-glyph-sprite.png
PytestZhongwenWendang/img/annotator-icon-sprite.png
PytestZhongwenWendang/img/apple-touch-icon.png
PytestZhongwenWendang/img/cancelfullscreen.png
PytestZhongwenWendang/img/close.png
PytestZhongwenWendang/img/fullscreen.png
PytestZhongwenWendang/img/loader.gif
PytestZhongwenWendang/img/menu-icon.png
PytestZhongwenWendang/img/save.png
PytestZhongwenWendang/img/saved.png
PytestZhongwenWendang/img/settings-s.png
PytestZhongwenWendang/img/settings.png
PytestZhongwenWendang/img/star.png
PytestZhongwenWendang/js/__init__.py
PytestZhongwenWendang/js/epub.js
PytestZhongwenWendang/js/epub.min.js
PytestZhongwenWendang/js/epub.min.map
PytestZhongwenWendang/js/hooks.min.js
PytestZhongwenWendang/js/hooks.min.map
PytestZhongwenWendang/js/reader.js
PytestZhongwenWendang/js/reader.js.map
PytestZhongwenWendang/js/reader.min.js
PytestZhongwenWendang/js/reader.min.map
PytestZhongwenWendang/js/hooks/__init__.py
PytestZhongwenWendang/js/hooks/extensions/__init__.py
PytestZhongwenWendang/js/hooks/extensions/highlight.js
PytestZhongwenWendang/js/libs/__init__.py
PytestZhongwenWendang/js/libs/jquery.min.js
PytestZhongwenWendang/js/libs/localforage.min.js
PytestZhongwenWendang/js/libs/screenfull.js
PytestZhongwenWendang/js/libs/screenfull.min.js
PytestZhongwenWendang/js/libs/zip.min.js
PytestZhongwenWendang/js/plugins/__init__.py
pytest_zhongwen_wendang-2024.3.4.0.dist-info/METADATA
pytest_zhongwen_wendang-2024.3.4.0.dist-info/WHEEL
pytest_zhongwen_wendang-2024.3.4.0.dist-info/entry_points.txt
pytest_zhongwen_wendang-2024.3.4.0.dist-info/top_level.txt
pytest_zhongwen_wendang-2024.3.4.0.dist-info/RECORD
